qwert/__init__.py
qwert/base64.py
qwert/cli.py
qwert/dict_fn.py
qwert/django_orm.py
qwert/ethereum.py
qwert/file_cache.py
qwert/file_fn.py
qwert/list_fn.py
qwert/net.py
qwert/random_user.py
qwert/salt.py
qwert/text_fn.py
qwert-2.4.0.dist-info/LICENSE
qwert-2.4.0.dist-info/METADATA
qwert-2.4.0.dist-info/WHEEL
qwert-2.4.0.dist-info/top_level.txt
qwert-2.4.0.dist-info/RECORD
