Metadata-Version: 2.1
Name: qwert
Version: 2.4.0
Summary: Python extensions: list/dict/file...
Home-page: https://github.com/voken100g/python-qwert
Author: Vision Network
Author-email: michael@vision.network
License: UNKNOWN
Keywords: Python,Extensions,List,Dict,File
Platform: UNKNOWN
Classifier: Programming Language :: Python :: 3
Classifier: License :: OSI Approved :: MIT License
Classifier: Operating System :: OS Independent
Requires-Dist: cli-print
Requires-Dist: requests
Requires-Dist: pyperclip
Requires-Dist: web3
Requires-Dist: pysha3
Requires-Dist: ecdsa
